warprouter/__init__.py
warprouter/router.py
warprouter-0.1.1.dist-info/LICENSE
warprouter-0.1.1.dist-info/METADATA
warprouter-0.1.1.dist-info/WHEEL
warprouter-0.1.1.dist-info/top_level.txt
warprouter-0.1.1.dist-info/RECORD
