Metadata-Version: 2.1
Name: warprouter
Version: 0.1.1
Summary: A Python library for managing Cloudflare WARP routing on Windows
Home-page: https://github.com/dogagcmnr/warprouter
Author: Doga Gocmener
Author-email: gocmenerdoga@gmail.com
Classifier: Programming Language :: Python :: 3
Classifier: License :: OSI Approved :: MIT License
Classifier: Operating System :: Microsoft :: Windows
Classifier: Topic :: System :: Networking
Requires-Python: >=3.6
License-File: LICENSE
Requires-Dist: psutil>=5.8.0
Requires-Dist: pywin32>=228; platform_system == "Windows"
